broker_grpc_lib/__init__.py
broker_grpc_lib/exc/__init__.py
broker_grpc_lib/exc/no_queue_exception.py
broker_grpc_lib/lib/__init__.py
broker_grpc_lib/lib/broker_handler.py
broker_grpc_lib/lib/grpc_client.py
broker_grpc_lib/lib/rabbitmq_handler.py
tests/__init__.py
tests/functional/__init__.py
tests/functional/test_rabbitmq_handler.py
tests/helpers/__init__.py
tests/helpers/async_iterator.py
tests/helpers/grpc_stub.py
tests/units/__init__.py
tests/units/test_grpc_client.py
tests/units/test_rabbitmq_handler.py
broker_grpc_lib-0.4.1.dist-info/METADATA
broker_grpc_lib-0.4.1.dist-info/WHEEL
broker_grpc_lib-0.4.1.dist-info/top_level.txt
broker_grpc_lib-0.4.1.dist-info/RECORD
