Metadata-Version: 2.1
Name: broker-grpc-lib
Version: 0.4.1
Summary: Python package for easier use message brokers with gRPC application
Author: multiadmin_optimus_prime
Author-email: evgenykond@gmail.com
Classifier: Programming Language :: Python :: 3.10
Classifier: Intended Audience :: Developers
Classifier: Development Status :: 4 - Beta
Classifier: Operating System :: OS Independent
Classifier: Topic :: Software Development :: Libraries :: Python Modules
Requires-Dist: pydantic (>=1.10.4)
Requires-Dist: aio-pika (>=9.0.5)
Requires-Dist: grpcio (>=1.46.3)
